fastdatetime-0.3.2.dist-info/METADATA
fastdatetime-0.3.2.dist-info/WHEEL
fastdatetime-0.3.2.dist-info/license_files/LICENSE-APACHE
fastdatetime-0.3.2.dist-info/license_files/LICENSE-MIT
fastdatetime/__init__.py
fastdatetime/fastdatetime.cp38-win_amd64.pyd
fastdatetime-0.3.2.dist-info/RECORD
