Metadata-Version: 2.1
Name: fastdatetime
Version: 0.3.2
Classifier: Development Status :: 4 - Beta
Classifier: Programming Language :: Python
License-File: LICENSE-APACHE
License-File: LICENSE-MIT
Summary: Like datetime, but fast
Keywords: datetime,parsing,iso8601,rfc3339
License: MIT OR Apache-2.0
Requires-Python: >=3.7
